pysmarthome-server.wsgi
setup.py
pysmarthome_server/__init__.py
pysmarthome_server/config.example.py
pysmarthome_server.egg-info/PKG-INFO
pysmarthome_server.egg-info/SOURCES.txt
pysmarthome_server.egg-info/dependency_links.txt
pysmarthome_server.egg-info/not-zip-safe
pysmarthome_server.egg-info/requires.txt
pysmarthome_server.egg-info/top_level.txt
pysmarthome_server/db/__init__.py
pysmarthome_server/db/db.py
pysmarthome_server/graphql/__init__.py
pysmarthome_server/graphql/mutation_resolvers.py
pysmarthome_server/graphql/query_resolvers.py
pysmarthome_server/graphql/schema.py
pysmarthome_server/graphql/type_resolvers.py
pysmarthome_server/graphql/utils.py
pysmarthome_server/handlers/__init__.py
pysmarthome_server/handlers/scheduler.py
pysmarthome_server/middlewares/__init__.py
pysmarthome_server/middlewares/auth.py