Metadata-Version: 2.1
Name: pysmarthome-server
Version: 0.3.0
Summary: A simple yet powerful python http server to integrate smart devices
Home-page: https://github.com/filipealvesdef/pysmarthome-server
Author: Filipe Alves
Author-email: filipe.alvesdefernando@gmail.com
License: UNKNOWN
Platform: UNKNOWN
